jbiot/__init__.py
jbiot/active.py
jbiot/arrange.py
jbiot/dict2yaml.py
jbiot/docker2sing.py
jbiot/filterTable.py
jbiot/func.macro
jbiot/func.macro.bark
jbiot/get_template.py
jbiot/handleTemplate.py
jbiot/jbiotWorker.py
jbiot/jsondb.py
jbiot/logmove.py
jbiot/logrun.py
jbiot/logrun2.py
jbiot/md2html.py
jbiot/mkdocsTemplate.tgz
jbiot/render.py
jbiot/report.py
jbiot/run.cmd
jbiot/skeleton.py
jbiot/smartFqs.py
jbiot/smartPair.py
jbiot/yamladd.py
jbiot/jbio/__init__.py
jbiot/jbio/jbio.py
jbiot/jbio/jmail.py
jbiot/jbio/sysinfo.py
jbiot/pipdog/pipdog.py
jbiot/pipdog/test.yaml
jbiot/pipdog/test_pipdog.py
jbiot/render/__init__.py
jbiot/render/add_html.py
jbiot/render/add_pdf.py
jbiot/render/add_png.py
jbiot/render/add_pngs.py
jbiot/render/add_svg.py
jbiot/render/add_text.py
jbiot/render/add_tsv.py
jbiot/render/add_xls.py
jbiot/render/func.macro
jbiot/render/out.md
jbiot/render/out.pdf
jbiot/render/out.png
jbiot/render/render.py
jbiot/render/svg.py
jbiot/render/test.md
jbiot/render/test.png
jbiot/render/test.svg
jbiot/render/test.svg.bark
jbiot/render/test.tsv
jbiot/render/test.txt
jbiot/render/test.xls
jbiot/render/test.yml
jbiot/render/test_render.sh
jbiot/startup/.travis.yml
jbiot/startup/__init__.py
jbiot/startup/app.templ
jbiot/startup/arrange.py
jbiot/startup/bin.py
jbiot/startup/conf.py
jbiot/startup/config.py
jbiot/startup/gitignore
jbiot/startup/index.rst
jbiot/startup/lsub_within_docker.py
jbiot/startup/main_within_docker.py
jbiot/startup/qc_report.py
jbiot/startup/qc_report_within_docker.py
jbiot/startup/qc_report_without_docker.py
jbiot/startup/report.py
jbiot/startup/setup.cfg
jbiot/startup/setup.py
jbiot/startup/stapp.py
jbiot/startup/starttest.py
jbiot/startup/startup.py
jbiot/startup/template.md
jbiot/startup/test.templ
jbiot/startup/test_arrange.py
jbiot/startup/test_main.py
jbiot/startup/test_report.py
jbiot/subjobs/__init__.py
jbiot/subjobs/cmd2showdoc.py
jbiot-1.5.5.dist-info/DESCRIPTION.rst
jbiot-1.5.5.dist-info/METADATA
jbiot-1.5.5.dist-info/RECORD
jbiot-1.5.5.dist-info/WHEEL
jbiot-1.5.5.dist-info/metadata.json
jbiot-1.5.5.dist-info/top_level.txt
