Metadata-Version: 2.0
Name: jbiot
Version: 1.5.5
Summary: Add a short description here!
Home-page: http://...
Author: KongDeju
Author-email: kongdeju@gene.ac
License: none
Platform: UNKNOWN
Classifier: Development Status :: 4 - Beta
Classifier: Programming Language :: Python
Requires-Dist: JYTools
Requires-Dist: PyYaml
Requires-Dist: jinja2
Requires-Dist: xlrd
Requires-Dist: xlwt
Requires-Dist: docopt
Requires-Dist: mkdocs
Requires-Dist: pymdown-extensions
Requires-Dist: batchcompute-cli
Requires-Dist: oss2
